venvhelper/__init__.py
venvhelper/venvhelper.py
venvhelper-0.0.2.dist-info/METADATA
venvhelper-0.0.2.dist-info/WHEEL
venvhelper-0.0.2.dist-info/top_level.txt
venvhelper-0.0.2.dist-info/RECORD
