Metadata-Version: 2.1
Name: venvhelper
Version: 0.0.2
Requires-Dist: logclshelper
Requires-Dist: syshelper
